<?xml version="1.0" encoding="UTF-8"?> 
<!DOCTYPE  tiles-definitions PUBLIC 
    "-//Aapche Software Foundation//DTD Tiles Configuration 2.0//EN" 
    "http://tiles.apache.org/dtds/tiles-config_2_0.dtd"> 

<tiles-definitions> 
    
  <definition name="/member/agreement" extends="main"> 
        <put-attribute name="title" value="약관 내용" ></put-attribute> 
        <put-attribute name="body" value="/WEB-INF/views/member/agreement.jsp" /> 
    </definition>   
    <definition name="/member/create" extends="main"> 
        <put-attribute name="title" value="회원가입" ></put-attribute> 
        <put-attribute name="body" value="/WEB-INF/views/member/createForm.jsp" /> 
    </definition>
    <definition name="/member/delete" extends="main"> 
        <put-attribute name="title" value="회원 탈퇴" ></put-attribute> 
        <put-attribute name="body" value="/WEB-INF/views/member/deleteForm.jsp" /> 
    </definition>
    <definition name="/member/list" extends="main">
        <put-attribute name="title" value="회원목록" ></put-attribute> 
        <put-attribute name="body" value="/WEB-INF/views/member/list.jsp" /> 
    </definition>   
    <definition name="/member/loginForm" extends="main"> 
        <put-attribute name="title" value="로그인" ></put-attribute> 
        <put-attribute name="body" value="/WEB-INF/views/member/loginForm.jsp" /> 
    </definition>
    <definition name="/member/read" extends="main"> 
        <put-attribute name="title" value="나의 정보" ></put-attribute> 
        <put-attribute name="body" value="/WEB-INF/views/member/read.jsp" /> 
    </definition>
    <definition name="/member/updateInfoForm" extends="main"> 
        <put-attribute name="title" value="정보 수정" ></put-attribute> 
        <put-attribute name="body" value="/WEB-INF/views/member/updateInfoForm.jsp" /> 
    </definition>
    <definition name="/member/updatePasswdForm" extends="main"> 
        <put-attribute name="title" value="비밀번호 수정" ></put-attribute> 
        <put-attribute name="body" value="/WEB-INF/views/member/updatePasswdForm.jsp" /> 
    </definition>   
    <definition name="/member/passwordCheck" extends="main"> 
        <put-attribute name="title" value="비밀번호 확인" ></put-attribute> 
        <put-attribute name="body" value="/WEB-INF/views/member/passwordCheck.jsp" /> 
    </definition>   
    <definition name="/member/passwdError" extends="main"> 
        <put-attribute name="title" value="비밀번호 확인" ></put-attribute> 
        <put-attribute name="body" value="/WEB-INF/views/member/passwdError.jsp" /> 
    </definition>   
    
	
</tiles-definitions> 
